alecto.py
alecto-2.0.2.dist-info/METADATA
alecto-2.0.2.dist-info/WHEEL
alecto-2.0.2.dist-info/entry_points.txt
alecto-2.0.2.dist-info/top_level.txt
alecto-2.0.2.dist-info/RECORD
