Metadata-Version: 2.1
Name: alecto
Version: 2.0.2
Summary: Alecto is an advanced command-line tool for password hashing. With support for various hashing algorithms, including MD5, SHA-256, SHA-512, Argon2, and bcrypt, it offers flexibility and security. Users can choose algorithms, include custom salts, and specify hash lengths, making it a versatile solution for password hashing needs.
Home-page: https://github.com/saphiraaa/NetherMath
Author: Saphiraaa
Author-email: fredmarkivand@gmail.com
Classifier: Programming Language :: Python :: 3
Requires-Dist: argon2
Requires-Dist: argon2-cffi
Requires-Dist: bcrypt
Requires-Dist: numpy
Requires-Dist: passlib
Requires-Dist: uuid
